pan_os_duplicate_finder/__init__.py
pan_os_duplicate_finder/commands/__init__.py
pan_os_duplicate_finder/commands/create_settings.py
pan_os_duplicate_finder/commands/find_duplicates.py
pan_os_duplicate_finder/commands/show_version.py
pan_os_duplicate_finder/main.py
pan_os_duplicate_finder/utilities/__init__.py
pan_os_duplicate_finder/utilities/analysis.py
pan_os_duplicate_finder/utilities/settings.py
pan_os_duplicate_finder/version.py
pan_os_duplicate_finder-0.1.0.dist-info/LICENSE
pan_os_duplicate_finder-0.1.0.dist-info/METADATA
pan_os_duplicate_finder-0.1.0.dist-info/WHEEL
pan_os_duplicate_finder-0.1.0.dist-info/entry_points.txt
pan_os_duplicate_finder-0.1.0.dist-info/RECORD
