Metadata-Version: 2.1
Name: pan-os-duplicate-finder
Version: 0.1.0
Summary: A command-line tool to find duplicate address objects across PAN-OS device groups
License: Apache 2.0
Author: Calvin Remsburg
Author-email: cremsburg.dev@gmail.com
Requires-Python: >=3.10,<4.0
Classifier: License :: Other/Proprietary License
Classifier: Programming Language :: Python :: 3
Classifier: Programming Language :: Python :: 3.10
Classifier: Programming Language :: Python :: 3.11
Classifier: Programming Language :: Python :: 3.12
Requires-Dist: pan-os-python (>=1.11.0,<2.0.0)
Requires-Dist: pandas (>=2.2.0,<3.0.0)
Requires-Dist: pyyaml (>=6.0.1,<7.0.0)
Requires-Dist: rich (>=13.7.0,<14.0.0)
Requires-Dist: setuptools (>=75.8.0,<76.0.0)
Requires-Dist: tabulate (>=0.9.0,<0.10.0)
Requires-Dist: typer[all] (>=0.9.0,<0.10.0)
